valeiraConnect/__init__.py
valeiraConnect/llm.py
valeiraConnect-0.1.dist-info/LICENSE
valeiraConnect-0.1.dist-info/METADATA
valeiraConnect-0.1.dist-info/WHEEL
valeiraConnect-0.1.dist-info/top_level.txt
valeiraConnect-0.1.dist-info/RECORD
